musestudio/__init__.py
musestudio/convert_raw.py
musestudio/export_bids_files.py
musestudio/import_bids_files.py
musestudio/import_raw_files.py
musestudio/view.py
musestudio-0.1.0.dist-info/LICENSE
musestudio-0.1.0.dist-info/METADATA
musestudio-0.1.0.dist-info/WHEEL
musestudio-0.1.0.dist-info/top_level.txt
musestudio-0.1.0.dist-info/RECORD
